<?xml version="1.0" encoding="utf-8" ?><workflow xmlns="http://vmware.com/vco/workflow" xmlns:xsi="http://www.w3.org/2001/XMLSchema-instance" xsi:schemaLocation="http://vmware.com/vco/workflow http://vmware.com/vco/workflow/Workflow-v4.xsd" root-name="item1" object-name="workflow:name=generic" id="934bb3b6-5c37-39df-844c-b7e2372570ea" version="1.0.0" api-version="6.0.0" restartMode="1" resumeFromFailedMode="0"><display-name><![CDATA[TestWorkflow3]]></display-name><position x="105" y="45.90909090909091" /><input><param name="foo" type="string" /><param name="bar" type="string" /></input><output><param name="result" type="string" /></output><workflow-item name="item0" type="end" end-mode="0"><position x="425.0" y="45.40909090909091" /></workflow-item><workflow-item name="item1" out-name="item0" type="task"><display-name><![CDATA[test1]]></display-name><script encoded="false"><![CDATA[System.log("foo=" + foo + ", bar=" + bar);
result = "test result";
]]></script><in-binding><bind name="foo" type="string" export-name="foo" /><bind name="bar" type="string" export-name="bar" /></in-binding><out-binding><bind name="result" type="string" export-name="result" /></out-binding><position x="225.0" y="55.40909090909091" /></workflow-item><presentation><p-param name="foo"><desc><![CDATA[foo]]></desc><p-qual kind="static" name="mandatory" type="boolean"><![CDATA[true]]></p-qual></p-param><p-param name="bar"><desc><![CDATA[bar]]></desc><p-qual kind="static" name="mandatory" type="boolean"><![CDATA[true]]></p-qual></p-param></presentation></workflow>